MANIFEST.in
README.md
setup.cfg
setup.py
pdf2image/__init__.py
pdf2image/exceptions.py
pdf2image/generators.py
pdf2image/parsers.py
pdf2image/pdf2image.py
pdf2img.egg-info/PKG-INFO
pdf2img.egg-info/SOURCES.txt
pdf2img.egg-info/dependency_links.txt
pdf2img.egg-info/requires.txt
pdf2img.egg-info/top_level.txt