Metadata-Version: 2.1
Name: pdf2img
Version: 0.1.1
Summary: A wrapper around the pdftoppm and pdftocairo command line tools to convert PDF to a PIL Image list.
Home-page: https://github.com/Belval/pdf2image
Author: Roman Grigoriev
Author-email: hjklvfr@list.ru
License: UNKNOWN
Keywords: pdf image png jpeg jpg convert
Platform: UNKNOWN
Classifier: Development Status :: 5 - Production/Stable
Classifier: Programming Language :: Python :: 2
Classifier: Intended Audience :: Developers
Classifier: License :: OSI Approved :: MIT License
Classifier: Programming Language :: Python :: 3
Classifier: Programming Language :: Python :: 3.5
Classifier: Programming Language :: Python :: 3.6
Classifier: Programming Language :: Python :: 3.7
Classifier: Programming Language :: Python :: 3.8
